<annotation>
	<folder>labeled</folder>
	<filename>A.de85c867-e3d6-11ec-b0cd-c2604c9a72c0.jpg</filename>
	<path>C:\workspaces\vocal-phone\labeled\A.de85c867-e3d6-11ec-b0cd-c2604c9a72c0.jpg</path>
	<source>
		<database>Unknown</database>
	</source>
	<size>
		<width>2448</width>
		<height>3264</height>
		<depth>3</depth>
	</size>
	<segmented>0</segmented>
	<object>
		<name>A</name>
		<pose>Unspecified</pose>
		<truncated>0</truncated>
		<difficult>0</difficult>
		<bndbox>
			<xmin>1382</xmin>
			<ymin>968</ymin>
			<xmax>2300</xmax>
			<ymax>1718</ymax>
		</bndbox>
	</object>
</annotation>
